swarmauri_base/ComponentBase.py
swarmauri_base/DynamicBase.py
swarmauri_base/LoggerMixin.py
swarmauri_base/ObserveBase.py
swarmauri_base/ServiceMixin.py
swarmauri_base/YamlMixin.py
swarmauri_base/__init__.py
swarmauri_base/agents/AgentBase.py
swarmauri_base/agents/AgentConversationMixin.py
swarmauri_base/agents/AgentRetrieveMixin.py
swarmauri_base/agents/AgentSystemContextMixin.py
swarmauri_base/agents/AgentToolMixin.py
swarmauri_base/agents/AgentVectorStoreMixin.py
swarmauri_base/agents/__init__.py
swarmauri_base/chains/ChainBase.py
swarmauri_base/chains/ChainContextBase.py
swarmauri_base/chains/ChainStepBase.py
swarmauri_base/chains/PromptContextChainBase.py
swarmauri_base/chains/__init__.py
swarmauri_base/chunkers/ChunkerBase.py
swarmauri_base/chunkers/__init__.py
swarmauri_base/control_panels/ControlPanelBase.py
swarmauri_base/control_panels/__init__.py
swarmauri_base/conversations/ConversationBase.py
swarmauri_base/conversations/ConversationSystemContextMixin.py
swarmauri_base/conversations/__init__.py
swarmauri_base/dataconnectors/DataConnectorBase.py
swarmauri_base/dataconnectors/__init__.py
swarmauri_base/distances/DistanceBase.py
swarmauri_base/distances/VisionDistanceBase.py
swarmauri_base/distances/__init__.py
swarmauri_base/document_stores/DocumentStoreBase.py
swarmauri_base/document_stores/DocumentStoreRetrieveBase.py
swarmauri_base/document_stores/__init__.py
swarmauri_base/documents/DocumentBase.py
swarmauri_base/documents/__init__.py
swarmauri_base/embeddings/EmbeddingBase.py
swarmauri_base/embeddings/VisionEmbeddingBase.py
swarmauri_base/embeddings/__init__.py
swarmauri_base/evaluator_pools/EvaluatorPoolBase.py
swarmauri_base/evaluator_pools/__init__.py
swarmauri_base/evaluator_results/EvalResultBase.py
swarmauri_base/evaluator_results/__init__.py
swarmauri_base/evaluators/EvaluatorBase.py
swarmauri_base/evaluators/__init__.py
swarmauri_base/factories/FactoryBase.py
swarmauri_base/factories/_init__.py
swarmauri_base/glogging.py
swarmauri_base-0.7.5.dist-info/LICENSE
swarmauri_base-0.7.5.dist-info/METADATA
swarmauri_base-0.7.5.dist-info/WHEEL
swarmauri_base-0.7.5.dist-info/RECORD
