Metadata-Version: 2.3
Name: swarmauri-base
Version: 0.7.5
Summary: This repository includes base classes and mixins for the Swarmauri framework.
License: Apache-2.0
Author: Jacob Stewart
Author-email: jacob@swarmauri.com
Requires-Python: >=3.10,<3.13
Classifier: License :: OSI Approved :: Apache Software License
Classifier: Programming Language :: Python :: 3.10
Classifier: Programming Language :: Python :: 3.11
Classifier: Programming Language :: Python :: 3.12
Requires-Dist: numpy (>=1.26.4)
Requires-Dist: pandas (>=2.2)
Requires-Dist: pydantic (>=2.0)
Requires-Dist: pyyaml (>=6.0.2)
Requires-Dist: requests (>=2.0)
Requires-Dist: swarmauri_core
Requires-Dist: swarmauri_typing
